{"stats":{"minecraft:used":{"minecraft:oak_fence":47,"minecraft:grass_block":74,"minecraft:repeater":1,"minecraft:wildflowers":7,"minecraft:apple":6,"minecraft:stick":376,"minecraft:firework_rocket":126,"minecraft:honey_block":1,"minecraft:cut_copper":4,"minecraft:item_frame":1006,"minecraft:ender_eye":8,"minecraft:oak_sign":7,"minecraft:anvil":3,"minecraft:beetroot":5,"minecraft:petrified_oak_slab":21,"minecraft:command_block":119,"minecraft:carrot_on_a_stick":637,"minecraft:short_grass":94,"minecraft:goat_horn":4,"minecraft:lime_wool":4,"minecraft:torch":16,"minecraft:dirt":1,"minecraft:honey_bottle":2,"minecraft:decorated_pot":2,"minecraft:blue_wool":6,"minecraft:snow":1,"minecraft:red_wool":8,"minecraft:sweet_berries":1,"minecraft:oak_button":1,"minecraft:redstone_block":140,"minecraft:stone_button":4,"minecraft:bundle":10,"minecraft:debug_stick":176,"minecraft:crafter":66,"minecraft:birch_log":127,"minecraft:oak_log":11,"minecraft:stone":324,"minecraft:hopper":1,"minecraft:barrier":65,"minecraft:crafting_table":6,"minecraft:end_portal_frame":9,"minecraft:snowball":69,"minecraft:iron_chestplate":3,"minecraft:oak_planks":77,"minecraft:dropper":1,"minecraft:bow":93,"minecraft:armor_stand":25},"minecraft:killed_by":{"minecraft:phantom":1},"minecraft:killed":{"minecraft:zombie":2,"minecraft:villager":1},"minecraft:dropped":{"minecraft:glass_bottle":1,"minecraft:carrot_on_a_stick":9,"minecraft:apple":5,"minecraft:sweet_berries":58,"minecraft:cooked_beef":1,"minecraft:enderman_spawn_egg":1,"minecraft:oak_sign":1,"minecraft:bundle":2,"minecraft:stick":94,"minecraft:item_frame":8,"minecraft:slime_ball":4,"minecraft:stone":3,"minecraft:command_block_minecart":1,"minecraft:dried_kelp":2,"minecraft:command_block":1,"minecraft:cut_copper":4,"minecraft:beetroot":1,"minecraft:armor_stand":1},"minecraft:mined":{"minecraft:decorated_pot":1},"minecraft:custom":{"minecraft:pig_one_cm":25170,"minecraft:interact_with_crafting_table":6,"minecraft:time_since_rest":287627,"minecraft:inspect_dropper":7,"minecraft:walk_one_cm":857702,"minecraft:leave_game":172,"minecraft:damage_taken":3710,"minecraft:mob_kills":4,"minecraft:play_time":1953811,"minecraft:damage_dealt":40,"minecraft:jump":1432,"minecraft:time_since_death":287606,"minecraft:aviate_one_cm":614031,"minecraft:drop":93,"minecraft:sprint_one_cm":149900,"minecraft:inspect_hopper":2,"minecraft:fall_one_cm":25316,"minecraft:total_world_time":3899799,"minecraft:fly_one_cm":757052,"minecraft:interact_with_anvil":1,"minecraft:walk_on_water_one_cm":53,"minecraft:crouch_one_cm":37885,"minecraft:sneak_time":15166,"minecraft:deaths":9},"minecraft:picked_up":{"minecraft:sweet_berries":119,"minecraft:saddle":1,"minecraft:stone":15,"minecraft:command_block":3,"minecraft:torch":3,"minecraft:honey_bottle":1,"minecraft:carrot_on_a_stick":2,"minecraft:oak_log":1,"minecraft:redstone_block":2,"minecraft:slime_ball":6,"minecraft:cut_copper":6,"minecraft:anvil":7,"minecraft:armor_stand":9,"minecraft:stick":13,"minecraft:birch_sapling":93,"minecraft:cooked_beef":2,"minecraft:mangrove_propagule":20,"minecraft:oak_planks":128,"minecraft:honey_block":7,"minecraft:snowball":1,"minecraft:decorated_pot":1,"minecraft:repeater":8,"minecraft:bundle":2,"minecraft:dried_kelp":3,"minecraft:item_frame":3,"minecraft:oak_button":1,"minecraft:rotten_flesh":2,"minecraft:apple":104,"minecraft:glass_bottle":2,"minecraft:beetroot":2}},"DataVersion":4435}